setup.cfg
setup.py
Centaur.egg-info/PKG-INFO
Centaur.egg-info/SOURCES.txt
Centaur.egg-info/dependency_links.txt
Centaur.egg-info/not-zip-safe
Centaur.egg-info/top_level.txt
centaur/__init__.py
centaur/bridges.py
centaur/di.py
centaur/funcprog.py
centaur/queries.py
centaur/safe_import.py
centaur/switches.py
centaur/utils.py
centaur/version.py
centaur/applications/__init__.py
centaur/contrib/__init__.py
centaur/contrib/ping.py
centaur/datatypes/__init__.py
centaur/datatypes/classes.py
centaur/datatypes/context.py
centaur/datatypes/decorators.py
centaur/datatypes/defaults.py
centaur/datatypes/exceptions.py
centaur/datatypes/mixins.py
centaur/services/__init__.py