Metadata-Version: 1.1
Name: Centaur
Version: 0.3.3
Summary: General Purpose Python3 Application Framework (Port-Adapter Architecture)
Home-page: https://github.com/laco/python-centaur/
Author: László Andrási
Author-email: mail@laszloandrasi.com
License: Apache2.0
Download-URL: https://github.com/laco/python-centaur/tarball/0.3.3
Platform: any
Classifier: Development Status :: 4 - Beta
Classifier: Environment :: Web Environment
Classifier: Intended Audience :: Developers
Classifier: License :: OSI Approved :: BSD License
Classifier: Operating System :: OS Independent
Classifier: Programming Language :: Python
Classifier: Programming Language :: Python :: 3
Classifier: Topic :: Software Development :: Libraries :: Python Modules
